[
    {
       "drugId":"00001",
       "drugName":"ยาแคปซูลรากสามสิบ",
       "drugPackages":"กระปุก",
       "drugPrice":"100"
    },
    {
       "drugId":"00002",
       "drugName":"แคปซูลหญ้ารีแพร์",
       "drugPackages":"กระปุก",
       "drugPrice":"180"
    },
    {
       "drugId":"00003",
       "drugName":"แคปซูลหมามุ่ย",
       "drugPackages":"กระปุก",
       "drugPrice":"150"
    },
    {
       "drugId":"00004",
       "drugName":"ยาล้างลำไส้",
       "drugPackages":"ขวด",
       "drugPrice":"60"
    },
    {
       "drugId":"00005",
       "drugName":"แคปซูลประจำเดือนจะหมด",
       "drugPackages":"กระปุก",
       "drugPrice":"100"
    },
    {
       "drugId":"00006",
       "drugName":"แคปซูลตรีผลา",
       "drugPackages":"กระปุก",
       "drugPrice":"100"
    },
    {
       "drugId":"00007",
       "drugName":"แคปซูลธรณีสันฑะฆาต",
       "drugPackages":"กระปุก",
       "drugPrice":"100"
    },
    {
       "drugId":"00008",
       "drugName":"แคปซูลเบญจกูล",
       "drugPackages":"กระปุก",
       "drugPrice":"100"
    },
    {
       "drugId":"00009",
       "drugName":"แคปซูลเลือดงาม",
       "drugPackages":"กระปุก",
       "drugPrice":"100"
    },
    {
       "drugId":"00011",
       "drugName":"แคปซูลปราบชมพูทวีป",
       "drugPackages":"กระปุก",
       "drugPrice":"100"
    },
    {
       "drugId":"00012",
       "drugName":"แคปซูลอัมฤควาที",
       "drugPackages":"กระปุก",
       "drugPrice":"100"
    },
    {
       "drugId":"00013",
       "drugName":"แคปซูลเขียวหอม",
       "drugPackages":"กระปุก",
       "drugPrice":"100"
    },
    {
       "drugId":"00014",
       "drugName":"แคปซูลบำรุงโลหิต",
       "drugPackages":"กระปุก",
       "drugPrice":"100"
    },
    {
       "drugId":"00015",
       "drugName":"แคปซูลระย่อมลมสูง",
       "drugPackages":"กระปุก",
       "drugPrice":"120"
    },
    {
       "drugId":"00016",
       "drugName":"ชุดต้มตรีผลา",
       "drugPackages":"ห่อ",
       "drugPrice":"60"
    },
    {
       "drugId":"00018",
       "drugName":"แคปซูลธาตุบรรจบ",
       "drugPackages":"กระปุก",
       "drugPrice":"100"
    },
    {
       "drugId":"00019",
       "drugName":"ยาแคปซูลป่าแฮวหมอง",
       "drugPackages":"กระปุก",
       "drugPrice":"100"
    },
    {
       "drugId":"00020",
       "drugName":"แคปซูลกลีบบัวแดง",
       "drugPackages":"กระปุก",
       "drugPrice":"100"
    },
    {
       "drugId":"00021",
       "drugName":"สมุนไพรอบตัว",
       "drugPackages":"ห่อ",
       "drugPrice":"90"
    },
    {
       "drugId":"00022",
       "drugName":"ชาชงหญ้ารีแพร์",
       "drugPackages":"ซอง",
       "drugPrice":"40"
    },
    {
       "drugId":"8852913200914",
       "drugName":"ยาน้ำแก้ร้อนในเขากุย240ซีซี.",
       "drugPackages":"ขวด",
       "drugPrice":"45"
    },
    {
       "drugId":"8853353200816",
       "drugName":"แคปซูลกวาวเครือขาว",
       "drugPackages":"ขวด",
       "drugPrice":"240"
    },
    {
       "drugId":"8853353201417",
       "drugName":"แคปซูลว่านชักมดลูก",
       "drugPackages":"ขวด",
       "drugPrice":"200"
    },
    {
       "drugId":"8853353201714",
       "drugName":"แคปซูลกระชายดำ",
       "drugPackages":"ขวด",
       "drugPrice":"300"
    },
    {
       "drugId":"8853353300318",
       "drugName":"แคปซูลกระเทียม",
       "drugPackages":"ขวด",
       "drugPrice":"300"
    },
    {
       "drugId":"8853353301810",
       "drugName":"ผลิตภัณฑ์อาหารเสริมสารสกัดจากเมล็ดงาดำ",
       "drugPackages":"ขวด",
       "drugPrice":"400"
    },
    {
       "drugId":"8853353302213",
       "drugName":"ตังถั่งเฉ้า-พลัส",
       "drugPackages":"กล่อง",
       "drugPrice":"500"
    },
    {
       "drugId":"8855050100048",
       "drugName":"ยาครีมพริก",
       "drugPackages":"หลอด",
       "drugPrice":"80"
    },
    {
       "drugId":"8855050100079",
       "drugName":"ยาแคปซูลฟ้าทะลายโจร(บริสเตอร์)",
       "drugPackages":"กระปุก",
       "drugPrice":"80"
    },
    {
       "drugId":"8855050100147",
       "drugName":"ยาหม่องพญายอใหญ่",
       "drugPackages":"ขวด",
       "drugPrice":"60"
    },
    {
       "drugId":"8855050100154",
       "drugName":"ชาชงรางจืด",
       "drugPackages":"ห่อ",
       "drugPrice":"40"
    },
    {
       "drugId":"8855050100161",
       "drugName":"แคปซูลรางจืด",
       "drugPackages":"กระปุก",
       "drugPrice":"90"
    },
    {
       "drugId":"8855050100215",
       "drugName":"ยาหอมทิพโอสถ",
       "drugPackages":"ขวด",
       "drugPrice":"80"
    },
    {
       "drugId":"8855050100222",
       "drugName":"ยาแคปซูลจันทน์ลีลา",
       "drugPackages":"กระปุก",
       "drugPrice":"120"
    },
    {
       "drugId":"8855050100246",
       "drugName":"ยาแคปซูลประสะไพล",
       "drugPackages":"กระปุก",
       "drugPrice":"120"
    },
    {
       "drugId":"8855050100260",
       "drugName":"ยาระบายน้ำฝักคูณ 120 มล.",
       "drugPackages":"ขวด",
       "drugPrice":"40"
    },
    {
       "drugId":"8855050100284",
       "drugName":"ยาแคปซูลห้าราก",
       "drugPackages":"กระปุก",
       "drugPrice":"120"
    },
    {
       "drugId":"8855050100307",
       "drugName":"ยาหอมอินทจักร์",
       "drugPackages":"ขวด",
       "drugPrice":"80"
    },
    {
       "drugId":"8855050100321",
       "drugName":"ยาแคปซูลมะขามแขก",
       "drugPackages":"กล่อง",
       "drugPrice":"45"
    },
    {
       "drugId":"8855050100413",
       "drugName":"ยาแคปซูลสหัสธารา",
       "drugPackages":"กระปุก",
       "drugPrice":"90"
    },
    {
       "drugId":"8855050200014",
       "drugName":"ชาชงมะขามป้อม",
       "drugPackages":"ห่อ",
       "drugPrice":"40"
    },
    {
       "drugId":"8855050200038",
       "drugName":"ชาชงเถาวัลย์เปรียง",
       "drugPackages":"ห่อ",
       "drugPrice":"40"
    },
    {
       "drugId":"8855050200045",
       "drugName":"ชาชงบัวบก",
       "drugPackages":"ห่อ",
       "drugPrice":"55"
    },
    {
       "drugId":"8855050200069",
       "drugName":"ผลิตภัณฑ์อาหารเสริมน้ำมันรำข้าว",
       "drugPackages":"ขวด",
       "drugPrice":"550"
    },
    {
       "drugId":"8855539000005",
       "drugName":"ยาแคปซูลหญ้าปักกิ่ง",
       "drugPackages":"กระปุก",
       "drugPrice":"180"
    },
    {
       "drugId":"8855539000012",
       "drugName":"ยาแคปซูลเพชรสังฆาต",
       "drugPackages":"กระปุก",
       "drugPrice":"140"
    },
    {
       "drugId":"8855539000029",
       "drugName":"ยาแคปซูลบัวบก",
       "drugPackages":"กระปุก",
       "drugPrice":"140"
    },
    {
       "drugId":"8855539000036",
       "drugName":"ยาแคปซูลบอระเพ็ด",
       "drugPackages":"กระปุก",
       "drugPrice":"90"
    },
    {
       "drugId":"8855539000067",
       "drugName":"ยาแคปซูลเถาวัลย์เปรียง",
       "drugPackages":"กระปุก",
       "drugPrice":"90"
    },
    {
       "drugId":"8855539000074",
       "drugName":"ยาแคปซูลเพกา",
       "drugPackages":"กระปุก",
       "drugPrice":"90"
    },
    {
       "drugId":"8855539000081",
       "drugName":"แคปซูลยอ",
       "drugPackages":"กระปุก",
       "drugPrice":"90"
    },
    {
       "drugId":"8855539000104",
       "drugName":"ชาชงสมุนไพรหญ้าหนวดแมว",
       "drugPackages":"ห่อ",
       "drugPrice":"40"
    },
    {
       "drugId":"8855539000128",
       "drugName":"ชาชงชุมเห็ดเทศ",
       "drugPackages":"ห่อ",
       "drugPrice":"40"
    },
    {
       "drugId":"8855539000142",
       "drugName":"ชาชงกระเจี๊ยบ",
       "drugPackages":"ห่อ",
       "drugPrice":"40"
    },
    {
       "drugId":"8855539000159",
       "drugName":"ชาชงดอกคำฝอย",
       "drugPackages":"ห่อ",
       "drugPrice":"80"
    },
    {
       "drugId":"8855539000180",
       "drugName":"ยาแคปซูลมะระขี้นก",
       "drugPackages":"กระปุก",
       "drugPrice":"180"
    },
    {
       "drugId":"8855539000203",
       "drugName":"ยาแคปซูลขิง",
       "drugPackages":"กระปุก",
       "drugPrice":"90"
    },
    {
       "drugId":"8855539000210",
       "drugName":"ยาแคปซูลขมิ้นชัน (ใหญ่)",
       "drugPackages":"กระปุก",
       "drugPrice":"290"
    },
    {
       "drugId":"8855539000227",
       "drugName":"ยาแคปซูลฟ้าทะลายโจร(ใหญ่)",
       "drugPackages":"กระปุก",
       "drugPrice":"375"
    },
    {
       "drugId":"8855539002009",
       "drugName":"ยาครีมพญายอ",
       "drugPackages":"หลอด",
       "drugPrice":"30"
    },
    {
       "drugId":"8855539002016",
       "drugName":"คาลาไมน์พญายอ",
       "drugPackages":"ขวด",
       "drugPrice":"30"
    },
    {
       "drugId":"8855539002023",
       "drugName":"กลีเซอรีนพญายอ",
       "drugPackages":"ขวด",
       "drugPrice":"30"
    },
    {
       "drugId":"8855539002030",
       "drugName":"ยาหม่องพญายอ",
       "drugPackages":"ขวด",
       "drugPrice":"30"
    },
    {
       "drugId":"8855539002047",
       "drugName":"ตะไคร้หอมสเปรย์",
       "drugPackages":"ขวด",
       "drugPrice":"90"
    },
    {
       "drugId":"8855539002054",
       "drugName":"ตะไคร้หอมโลชั่น 120 มล.",
       "drugPackages":"ขวด",
       "drugPrice":"70"
    },
    {
       "drugId":"8855539002078",
       "drugName":"ยาหม่องตะไคร้หอม",
       "drugPackages":"ขวด",
       "drugPrice":"30"
    },
    {
       "drugId":"8855539002092",
       "drugName":"ครีมไพล",
       "drugPackages":"หลอด",
       "drugPrice":"30"
    },
    {
       "drugId":"8855539002108",
       "drugName":"น้ำมันไพล",
       "drugPackages":"ขวด",
       "drugPrice":"90"
    },
    {
       "drugId":"8855539002115",
       "drugName":"น้ำมันไพลกลิ่นมะกรูด",
       "drugPackages":"ขวด",
       "drugPrice":"90"
    },
    {
       "drugId":"8855539002139",
       "drugName":"ยาการ์ซิดีน",
       "drugPackages":"ขวด",
       "drugPrice":"45"
    },
    {
       "drugId":"8855539004010",
       "drugName":"สเปรย์ใบฝรั่ง",
       "drugPackages":"ขวด",
       "drugPrice":"60"
    },
    {
       "drugId":"8855539004430",
       "drugName":"ยาอมแก้ไอมะขามป้อม สูตร2",
       "drugPackages":"กระปุก",
       "drugPrice":"40"
    },
    {
       "drugId":"8855539010073",
       "drugName":"ครีมบัวบก",
       "drugPackages":"หลอด",
       "drugPrice":"35"
    },
    {
       "drugId":"8855539010103",
       "drugName":"ยาแคปซูลขมิ้นชัน(บริสเตอร์)",
       "drugPackages":"กล่อง",
       "drugPrice":"80"
    },
    {
       "drugId":"8855539010127",
       "drugName":"ยาแก้ไอมะขามป้อม",
       "drugPackages":"ขวด",
       "drugPrice":"40"
    },
    {
       "drugId":"8855539010158",
       "drugName":"ยาแคปซูลขมิ้นชัน",
       "drugPackages":"กระปุก",
       "drugPrice":"80"
    },
    {
       "drugId":"8855539010165",
       "drugName":"ยาแคปซูลฟ้าทะลายโจร",
       "drugPackages":"กระปุก",
       "drugPrice":"80"
    },
    {
       "drugId":"8855539010264",
       "drugName":"ยาหอมเทพจิตร",
       "drugPackages":"ขวด",
       "drugPrice":"80"
    },
    {
       "drugId":"8855539010301",
       "drugName":"ยาหอมนวโกฐ",
       "drugPackages":"ขวด",
       "drugPrice":"120"
    },
    {
       "drugId":"8855539010363",
       "drugName":"มัสคูลเสปรย์",
       "drugPackages":"ขวด",
       "drugPrice":"120"
    },
    {
       "drugId":"8855539010448",
       "drugName":"ยาดม  ตราอภัยภูเบศร",
       "drugPackages":"หลอด",
       "drugPrice":"25"
    },
    {
       "drugId":"8855539030026",
       "drugName":"ชาชงมะตูม",
       "drugPackages":"ห่อ",
       "drugPrice":"40"
    },
    {
       "drugId":"8856570150018",
       "drugName":"ยาหอมเทพจิตร (ห้าม้า)",
       "drugPackages":"หลอด",
       "drugPrice":"20"
    }
 ]